faceoff/__init__.py
faceoff/app.py
faceoff/cli.py
faceoff/api/__init__.py
faceoff/api/client.py
faceoff/screens/__init__.py
faceoff/screens/game.py
faceoff/screens/player.py
faceoff/screens/pregame.py
faceoff/screens/schedule.py
faceoff/screens/standings.py
faceoff/screens/stats.py
faceoff/screens/teams.py
faceoff/widgets/__init__.py
faceoff/widgets/game_card.py
faceoff/widgets/play_by_play.py
faceoff/widgets/scoreboard.py
faceoff-0.2.1.dist-info/METADATA
faceoff-0.2.1.dist-info/WHEEL
faceoff-0.2.1.dist-info/entry_points.txt
faceoff-0.2.1.dist-info/licenses/LICENSE
faceoff-0.2.1.dist-info/RECORD
