Metadata-Version: 2.4
Name: faceoff
Version: 0.2.1
Summary: Terminal tool for watching hockey games
Project-URL: Homepage, https://vgreg.github.io/faceoff/
Project-URL: Repository, https://github.com/vgreg/faceoff
Project-URL: Documentation, https://vgreg.github.io/faceoff/
Author-email: Vincent Gregoire <vincent.gregoire@gmail.com>
License-File: LICENSE
Keywords: python
Classifier: Intended Audience :: Developers
Classifier: Programming Language :: Python
Classifier: Programming Language :: Python :: 3
Classifier: Programming Language :: Python :: 3.10
Classifier: Programming Language :: Python :: 3.11
Classifier: Programming Language :: Python :: 3.12
Classifier: Programming Language :: Python :: 3.13
Classifier: Programming Language :: Python :: 3.14
Classifier: Topic :: Software Development :: Libraries :: Python Modules
Requires-Python: <4.0,>=3.10
Requires-Dist: httpx>=0.28.0
Requires-Dist: nhl-stats-api-client>=1.0.0
Requires-Dist: textual>=3.0.0
